privy/__init__.py
privy/core.py
privy/utils.py
privy/__pycache__/__init__.cpython-35.pyc
privy/__pycache__/utils.cpython-35.pyc
privy-6.0.0.dist-info/DESCRIPTION.rst
privy-6.0.0.dist-info/METADATA
privy-6.0.0.dist-info/RECORD
privy-6.0.0.dist-info/WHEEL
privy-6.0.0.dist-info/metadata.json
privy-6.0.0.dist-info/top_level.txt
tests/__init__.py
tests/test_privy.py
tests/__pycache__/__init__.cpython-35.pyc
tests/__pycache__/test_privy.cpython-35-PYTEST.pyc
