Metadata-Version: 2.0
Name: privy
Version: 6.0.0
Summary: Password-protected data made easy.
Home-page: https://github.com/ofek/privy
Author: Ofek Lev
Author-email: ofekmeister@gmail.com
License: MIT/Apache-2.0
Keywords: passwords,secrets,encryption,keys,aes,hmac
Platform: UNKNOWN
Classifier: Development Status :: 5 - Production/Stable
Classifier: Intended Audience :: Developers
Classifier: License :: OSI Approved :: MIT License
Classifier: License :: OSI Approved :: Apache Software License
Classifier: Natural Language :: English
Classifier: Operating System :: OS Independent
Classifier: Programming Language :: Python :: 2.7
Classifier: Programming Language :: Python :: 3.4
Classifier: Programming Language :: Python :: 3.5
Classifier: Programming Language :: Python :: 3.6
Classifier: Programming Language :: Python :: Implementation :: CPython
Classifier: Programming Language :: Python :: Implementation :: PyPy
Requires-Dist: argon2-cffi
Requires-Dist: cryptography
